ml_shap_xai/__init__.py
ml_shap_xai/text_reader.py
ml_shap_xai/data/my_code.py
ml_shap_xai-0.1.dist-info/METADATA
ml_shap_xai-0.1.dist-info/WHEEL
ml_shap_xai-0.1.dist-info/top_level.txt
ml_shap_xai-0.1.dist-info/RECORD
