Metadata-Version: 2.1
Name: ml-shap-xai
Version: 0.1
Summary: Code for XAI using Shap (Breast Cancer Dataset)
Home-page: https://github.com/savioratharv/prac_testing
Author: davinci003
Author-email: freegpt00@gmail.com
